MarketData/__init__.py
MarketData/config/logging_config.py
MarketData/config/spciq-api-marketdata-application.properties
MarketData/constants/config_constants.py
MarketData/constants/data_config.py
MarketData/constants/functions_constants.py
MarketData/constants/mnemonics_constants.py
MarketData/services/sdk_marketdata_interface.py
MarketData/services/helper/data_transform.py
MarketData/services/impl/sdk_marketdata_services_impl.py
MarketData/util/property_utils.py
marketdatatestdistribution-1.0.2.dist-info/METADATA
marketdatatestdistribution-1.0.2.dist-info/WHEEL
marketdatatestdistribution-1.0.2.dist-info/top_level.txt
marketdatatestdistribution-1.0.2.dist-info/RECORD
